amd_hipcim/__init__.py
amd_hipcim-0.0.2.dist-info/METADATA
amd_hipcim-0.0.2.dist-info/WHEEL
amd_hipcim-0.0.2.dist-info/top_level.txt
amd_hipcim-0.0.2.dist-info/RECORD
