Metadata-Version: 2.4
Name: amd-hipcim
Version: 0.0.2
Summary: hipCIM - an extensible toolkit designed to provide GPU accelerated I/O, computer vision & image processing primitives for N-Dimensional images with a focus on biomedical imaging.
Author-email: AMD <support@amd.com>
License: Apache 2.0
Project-URL: Homepage, https://rocm.docs.amd.com/projects/hipcim/en/latest/
Project-URL: Documentation, https://rocm.docs.amd.com/projects/hipcim/en/latest/reference/hipcim/index.html#hipcim-reference
Requires-Python: >=3.8
